CHANGES
LICENSE
MANIFEST.in
README.rst
setup.py
fingui/__init__.py
fingui/entry.py
fingui/event.py
fingui/eventTest.py
fingui/label.py
fingui/menu.py
fingui/popup.py
fingui/progressbar.py
fingui/tk.py
fingui.egg-info/PKG-INFO
fingui.egg-info/SOURCES.txt
fingui.egg-info/dependency_links.txt
fingui.egg-info/top_level.txt