Metadata-Version: 1.1
Name: fingui
Version: 0.2.2
Summary: A Pythonic Wrapper for Tkinter
Home-page: https://github.com/TaylorSMarks/FinGUI
Author: Taylor Marks
Author-email: taylor@marksfam.com
License: MIT
Keywords: gui tkinter ui ux widget widgets wrapper
Platform: UNKNOWN
Classifier: Development Status :: 1 - Planning
Classifier: Intended Audience :: Developers
Classifier: License :: OSI Approved :: MIT License
Classifier: Operating System :: OS Independent
Classifier: Programming Language :: Python :: 2
Classifier: Programming Language :: Python :: 2.6
Classifier: Programming Language :: Python :: 2.7
Classifier: Topic :: Software Development :: Libraries :: Application Frameworks
